whispr/__about__.py
whispr/__init__.py
whispr/aws.py
whispr/azure.py
whispr/cli.py
whispr/enums.py
whispr/factory.py
whispr/gcp.py
whispr/logging.py
whispr/vault.py
whispr/utils/crypto.py
whispr/utils/io.py
whispr/utils/process.py
whispr/utils/vault.py
whispr-0.8.0.dist-info/METADATA
whispr-0.8.0.dist-info/WHEEL
whispr-0.8.0.dist-info/entry_points.txt
whispr-0.8.0.dist-info/licenses/LICENSE
whispr-0.8.0.dist-info/RECORD
