Metadata-Version: 2.4
Name: whispr
Version: 0.8.0
Summary: A CLI tool to whisper your secrets between secure vault and your local environment
Project-URL: Documentation, https://github.com/cybrota/whispr/blob/main/README.md
Project-URL: Issues, https://github.com/cybrota/whispr/issues
Project-URL: Source, https://github.com/cybrota/whispr
Author-email: Naren Yellavula <naren.yellavula@gmail.com>
License-Expression: MIT
License-File: LICENSE
Keywords: code-security,cybersecurity,devsecops,mitre-attack-framework,no-plain-secrets,whispr
Classifier: Development Status :: 4 - Beta
Classifier: Programming Language :: Python
Classifier: Programming Language :: Python :: 3.8
Classifier: Programming Language :: Python :: 3.9
Classifier: Programming Language :: Python :: 3.10
Classifier: Programming Language :: Python :: 3.11
Classifier: Programming Language :: Python :: 3.12
Classifier: Programming Language :: Python :: Implementation :: CPython
Classifier: Programming Language :: Python :: Implementation :: PyPy
Requires-Python: >=3.9
Requires-Dist: azure-identity==1.19.0
Requires-Dist: azure-keyvault==4.2.0
Requires-Dist: boto3==1.35.42
Requires-Dist: click==8.1.7
Requires-Dist: google-cloud-secret-manager==2.20.2
Requires-Dist: hvac==2.3.0
Requires-Dist: python-dotenv==1.0.1
Requires-Dist: pyyaml==6.0.2
Requires-Dist: structlog==24.4.0
